Workbook

Sheet INVESTMENT
B9: CONFIGURAÇÕES
B10: Salário | D10: 3000
B11: Sugestão de investimento (30%) | D11: =D10*30% -> 900
B13: INVETIMENTO MENSAL
B14: Quanto investir por mês? | D14: 900
B15: Por quantos anos? | D15: 3
B16: Taxa de rendimento mensal? | D16: 0.01057
B17: Patrimônio acumulado? | D17: =FV(D16,D15*12,D14*-1) -> 39178.218
B18: Dividendos mensais? | D18: =D17*D16 -> 414.11377
B20: CENÁRIOS | E20: Dividendo
B21: Quanto em 2 anos? | D21: =FV($D$16,2*12,$D$14*-1) -> 24440.894 | E21: =D21*$D$16 -> 258.34025
B22: Quanto em 5 anos? | D22: =FV($D$16,5*12,$D$14*-1) -> 74865.012 | E22: =D22*$D$16 -> 791.32318
B23: Quanto em 10 anos? | D23: =FV($D$16,10*12,$D$14*-1) -> 215554.94 | E23: =D23*$D$16 -> 2278.4157
B24: Quanto em 15 anos? | D24: =FV($D$16,15*12,$D$14*-1) -> 479946.19 | E24: =D24*$D$16 -> 5073.0312
B25: Quanto em 20 anos? | D25: =FV($D$16,20*12,$D$14*-1) -> 976802.92 | E25: =D25*$D$16 -> 10324.807
B26: Quanto em 25 anos? | D26: =FV($D$16,25*12,$D$14*-1) -> 1910519.9 | E26: =D26*$D$16 -> 20194.196
B27: Quanto em 30 anos? | D27: =FV($D$16,30*12,$D$14*-1) -> 3665205.7 | E27: =D27*$D$16 -> 38741.225
B30: PERFIL | C30: : | D30: Moderado
B31: VALOR A SER INVESTIDO POR MÊS | D31: =D14 -> 900
B33: TIPO DE FII | D33: Percentual sugerido | E33: Valores
B34: PAPEL | C34: #VALUE! | D34: =VLOOKUP($D$30&"-"&INFORMAÇÕES!D3,INFORMAÇÕES!B2:E20,4,FALSE) -> 0.32 | E34: =D34*$D$31 -> 288
B35: TIJOLO | C35: #VALUE! | D35: =VLOOKUP($D$30&"-"&INFORMAÇÕES!D4,INFORMAÇÕES!B3:E21,4,FALSE) -> 0.4 | E35: =D35*$D$31 -> 360
B36: HÍBRIDOS | C36: #VALUE! | D36: =VLOOKUP($D$30&"-"&INFORMAÇÕES!D5,INFORMAÇÕES!B4:E22,4,FALSE) -> 0.08 | E36: =D36*$D$31 -> 72
B37: FOFs | C37: #VALUE! | D37: =VLOOKUP($D$30&"-"&INFORMAÇÕES!D6,INFORMAÇÕES!B5:E23,4,FALSE) -> 0.1 | E37: =D37*$D$31 -> 90
B38: DESENVOVIMENTOS | C38: #VALUE! | D38: =VLOOKUP($D$30&"-"&INFORMAÇÕES!D7,INFORMAÇÕES!B6:E24,4,FALSE) -> 0.1 | E38: =D38*$D$31 -> 90
B39: HOTELARIAS | C39: #VALUE! | D39: =VLOOKUP($D$30&"-"&INFORMAÇÕES!D8,INFORMAÇÕES!B7:E25,4,FALSE) -> 0.1 | E39: =D39*$D$31 -> 90

Sheet INFORMAÇÕES
B2: CHAVE | C2: PERFIL | D2: TIPOS DE FIIs | E2: %
B3: =C3&"-"&D3 -> Conservador-PAPEL | C3: Conservador | D3: PAPEL | E3: 0.3
B4: =C4&"-"&D4 -> Conservador-TIJOLO | C4: Conservador | D4: TIJOLO | E4: 0.5
B5: =C5&"-"&D5 -> Conservador-HÍBRIDOS | C5: Conservador | D5: HÍBRIDOS | E5: 0.1
B6: =C6&"-"&D6 -> Conservador-FOFs | C6: Conservador | D6: FOFs | E6: 0.1
B7: =C7&"-"&D7 -> Conservador-DESENVOVIMENTOS | C7: Conservador | D7: DESENVOVIMENTOS | E7: 0
B8: =C8&"-"&D8 -> Conservador-HOTELARIAS | C8: Conservador | D8: HOTELARIAS | E8: 0
B9: =C9&"-"&D9 -> Moderado-PAPEL | C9: Moderado | D9: PAPEL | E9: 0.32
B10: =C10&"-"&D10 -> Moderado-TIJOLO | C10: Moderado | D10: TIJOLO | E10: 0.4
B11: =C11&"-"&D11 -> Moderado-HÍBRIDOS | C11: Moderado | D11: HÍBRIDOS | E11: 0.08
B12: =C12&"-"&D12 -> Moderado-FOFs | C12: Moderado | D12: FOFs | E12: 0.1
B13: =C13&"-"&D13 -> Moderado-DESENVOVIMENTOS | C13: Moderado | D13: DESENVOVIMENTOS | E13: 0.1
B14: =C14&"-"&D14 -> Moderado-HOTELARIAS | C14: Moderado | D14: HOTELARIAS | E14: 0.1
... B20: =C20&"-"&D20 -> Agressivo-HOTELARIAS | C20: Agressivo | D20: HOTELARIAS | E20: 0.1
